{
  "project_info": {
    "project_number": "868199089803",
    "project_id": "aeroxe-bee",
    "storage_bucket": "aeroxe-bee.firebasestorage.app"
  },
  "client": [
    {
      "client_info": {
        "mobilesdk_app_id": "1:868199089803:android:a287c8d6acf6403576f68e",
        "android_client_info": {
          "package_name": "com.aeroxebee.client"
        }
      },
      "oauth_client": [],
      "api_key": [
        {
          "current_key": "AIzaSyD5wBcCqp9iMxOxn8O5fSJeEeTRZHVDOWE"
        }
      ],
      "services": {
        "appinvite_service": {
          "other_platform_oauth_client": []
        }
      }
    }
  ],
  "configuration_version": "1"
}